revjo/__init__.py
revjo/_cli.py
revjo/revjo.py
revjo/version.py
revjo-0.1.dist-info/LICENSE
revjo-0.1.dist-info/METADATA
revjo-0.1.dist-info/WHEEL
revjo-0.1.dist-info/entry_points.txt
revjo-0.1.dist-info/top_level.txt
revjo-0.1.dist-info/RECORD
