Metadata-Version: 2.1
Name: revjo
Version: 0.1
Summary: reverse jo
Home-page: https://github.com/wtnb75/revjo
Author: Watanabe Takashi
Author-email: wtnb75@gmail.com
License: MIT
Platform: UNKNOWN
Classifier: Development Status :: 3 - Alpha
Classifier: Intended Audience :: Developers
Classifier: License :: OSI Approved :: MIT License
Classifier: Programming Language :: Python :: 3
Requires-Dist: click
